[
  {
    "webid": "golf-613",
    "name": "romeo-584",
    "description": "mike-910",
    "path": "uniform-467",
    "assetdatabase_webid": "golf-692"
  },
  {
    "webid": "oscar-730",
    "name": "echo-357",
    "description": "lima-372",
    "path": "zulu-133",
    "assetdatabase_webid": "whiskey-343"
  },
  {
    "webid": "sierra-513",
    "name": "oscar-408",
    "description": "golf-525",
    "path": "bravo-463",
    "assetdatabase_webid": "quebec-901"
  },
  {
    "webid": "papa-228",
    "name": "whiskey-428",
    "description": "sierra-831",
    "path": "mike-201",
    "assetdatabase_webid": "mike-720"
  }
]
