[
  {
    "createdBy": "juliet-808",
    "createdDateTime": "uniform-343",
    "createdOn": "echo-758",
    "description": "quebec-517",
    "endDate": "lima-738",
    "externalCode": "tango-386",
    "lastModifiedBy": "hotel-949",
    "lastModifiedDateTime": "romeo-606",
    "lastModifiedOn": "charlie-914",
    "name": "delta-404",
    "startDate": "oscar-617",
    "status": "echo-981"
  },
  {
    "createdBy": "tango-135",
    "createdDateTime": "tango-621",
    "createdOn": "golf-906",
    "description": "bravo-981",
    "endDate": "xray-987",
    "externalCode": "kilo-516",
    "lastModifiedBy": "golf-562",
    "lastModifiedDateTime": "charlie-364",
    "lastModifiedOn": "lima-360",
    "name": "november-141",
    "startDate": "golf-782",
    "status": "kilo-345"
  },
  {
    "createdBy": "charlie-195",
    "createdDateTime": "golf-717",
    "createdOn": "kilo-666",
    "description": "india-364",
    "endDate": "india-884",
    "externalCode": "echo-735",
    "lastModifiedBy": "kilo-263",
    "lastModifiedDateTime": "quebec-885",
    "lastModifiedOn": "kilo-643",
    "name": "kilo-465",
    "startDate": "victor-263",
    "status": "victor-957"
  },
  {
    "createdBy": "xray-419",
    "createdDateTime": "tango-207",
    "createdOn": "lima-510",
    "description": "juliet-915",
    "endDate": "november-253",
    "externalCode": "charlie-438",
    "lastModifiedBy": "whiskey-545",
    "lastModifiedDateTime": "golf-502",
    "lastModifiedOn": "echo-722",
    "name": "tango-613",
    "startDate": "xray-715",
    "status": "lima-529"
  }
]
