[
  {
    "questionId": 40108,
    "jobReqId": 7939,
    "locale": "delta-283",
    "order": 638,
    "questionName": "victor-950",
    "questionDescription": "charlie-130",
    "questionType": "quebec-994",
    "jobReqContent": "romeo-654",
    "expectedDir": "golf-237",
    "expectedAnswerValue": 934.18,
    "questionWeight": 953.95,
    "ratingScale": "november-369",
    "maxLength": 27959,
    "required": true,
    "score": true,
    "disqualifier": false,
    "questionParentId": 26255,
    "questionParentResponse": "oscar-883"
  },
  {
    "questionId": 90426,
    "jobReqId": 57053,
    "locale": "foxtrot-941",
    "order": 78514,
    "questionName": "kilo-300",
    "questionDescription": "mike-337",
    "questionType": "charlie-951",
    "jobReqContent": "bravo-842",
    "expectedDir": "zulu-227",
    "expectedAnswerValue": 848.21,
    "questionWeight": 375.99,
    "ratingScale": "quebec-406",
    "maxLength": 6591,
    "required": false,
    "score": true,
    "disqualifier": true,
    "questionParentId": 58973,
    "questionParentResponse": "papa-330"
  },
  {
    "questionId": 3185,
    "jobReqId": 52700,
    "locale": "papa-647",
    "order": 80019,
    "questionName": "kilo-960",
    "questionDescription": "whiskey-205",
    "questionType": "oscar-918",
    "jobReqContent": "yankee-422",
    "expectedDir": "uniform-748",
    "expectedAnswerValue": 452.78,
    "questionWeight": 476.76,
    "ratingScale": "tango-809",
    "maxLength": 67552,
    "required": true,
    "score": true,
    "disqualifier": false,
    "questionParentId": 97402,
    "questionParentResponse": "echo-335"
  },
  {
    "questionId": 6982,
    "jobReqId": 66378,
    "locale": "echo-594",
    "order": 86103,
    "questionName": "whiskey-890",
    "questionDescription": "alpha-421",
    "questionType": "romeo-310",
    "jobReqContent": "charlie-293",
    "expectedDir": "romeo-708",
    "expectedAnswerValue": 819.78,
    "questionWeight": 889.48,
    "ratingScale": "yankee-681",
    "maxLength": 76115,
    "required": false,
    "score": false,
    "disqualifier": false,
    "questionParentId": 76231,
    "questionParentResponse": "alpha-765"
  }
]
