[
  {
    "effectiveStartDate": "yankee-602",
    "id": "kilo-462",
    "createdBy": "november-294",
    "createdDateTime": "romeo-360",
    "displayOrder": "juliet-222",
    "effectiveEndDate": "india-345",
    "lastModifiedBy": "tango-689",
    "lastModifiedDateTime": "mike-209",
    "name": "golf-397",
    "status": "victor-758"
  },
  {
    "effectiveStartDate": "victor-128",
    "id": "delta-433",
    "createdBy": "oscar-717",
    "createdDateTime": "tango-216",
    "displayOrder": "lima-427",
    "effectiveEndDate": "alpha-394",
    "lastModifiedBy": "foxtrot-664",
    "lastModifiedDateTime": "bravo-150",
    "name": "romeo-271",
    "status": "india-947"
  },
  {
    "effectiveStartDate": "golf-736",
    "id": "juliet-371",
    "createdBy": "mike-735",
    "createdDateTime": "india-835",
    "displayOrder": "oscar-851",
    "effectiveEndDate": "hotel-959",
    "lastModifiedBy": "xray-881",
    "lastModifiedDateTime": "echo-736",
    "name": "juliet-518",
    "status": "yankee-711"
  },
  {
    "effectiveStartDate": "alpha-596",
    "id": "tango-334",
    "createdBy": "alpha-843",
    "createdDateTime": "xray-248",
    "displayOrder": "kilo-281",
    "effectiveEndDate": "quebec-688",
    "lastModifiedBy": "xray-139",
    "lastModifiedDateTime": "india-874",
    "name": "echo-685",
    "status": "mike-773"
  }
]
